tabulens/__init__.py
tabulens/__main__.py
tabulens/extractor.py
tabulens/utils/logger.py
tabulens-0.2.1.dist-info/METADATA
tabulens-0.2.1.dist-info/WHEEL
tabulens-0.2.1.dist-info/entry_points.txt
tabulens-0.2.1.dist-info/licenses/LICENSE
tabulens-0.2.1.dist-info/licenses/NOTICE
tabulens-0.2.1.dist-info/RECORD
