Metadata-Version: 2.4
Name: tabulens
Version: 0.2.1
Summary: LLM-powered PDF table extractor
Project-URL: Homepage, https://github.com/astonishedrobo/tabulens
Author-email: Soumyajit Basu <soumyajit.basu22@gmail.com>
License: 
License-File: LICENSE
License-File: NOTICE
Requires-Python: >=3.10
Requires-Dist: datasets>=3.6.0
Requires-Dist: huggingface-hub>=0.33.0
Requires-Dist: langchain-google-genai==2.1.4
Requires-Dist: langchain-groq==0.3.2
Requires-Dist: langchain-openai==0.3.11
Requires-Dist: langchain==0.3.21
Requires-Dist: numpy>=1.26.4
Requires-Dist: opencv-python>=4.10.0.84
Requires-Dist: pandas>=2.2.3
Requires-Dist: pdf2image>=1.17.0
Requires-Dist: pydantic>=2.10
Requires-Dist: python-dotenv
Requires-Dist: tqdm>=4.67.1
Requires-Dist: ultralytics>=8.3.156
